{
  "transform": {
    "^.+\\.(t|j)sx?$": "ts-jest",
    "\\.js$": "<rootDir>/node_modules/babel-jest"
  },
  "testRegex": "(/__tests__/.*|(\\.|/)(test|spec))\\.(jsx?|tsx?)$",
  "moduleFileExtensions": ["ts", "tsx", "js", "jsx", "json", "node"],
  "collectCoverage": true,
  "collectCoverageFrom": ["./src/**/*.ts"],
  "coveragePathIgnorePatterns": [
    "node_modules",
    "test-config",
    "interfaces",
    "jestGlobalMocks.ts",
    ".module.ts",
    "<rootDir>/src/index.ts",
    ".mock.ts"
  ],
  "coverageThreshold": {
    "global": {
      "branches": 1,
      "functions": 1,
      "lines": 1,
      "statements": 1
    }
  }
}